AUTHORS
CHANGES
LICENSE
MANIFEST.in
README.md
setup.py
cmsplugin_embedded_menu.egg-info/PKG-INFO
cmsplugin_embedded_menu.egg-info/SOURCES.txt
cmsplugin_embedded_menu.egg-info/dependency_links.txt
cmsplugin_embedded_menu.egg-info/requires.txt
cmsplugin_embedded_menu.egg-info/top_level.txt
cmsplugin_embeddedmenu/__init__.py
cmsplugin_embeddedmenu/cms_plugins.py
cmsplugin_embeddedmenu/models.py
cmsplugin_embeddedmenu/lib/__init__.py
cmsplugin_embeddedmenu/lib/choices.py
cmsplugin_embeddedmenu/lib/formatting.py
cmsplugin_embeddedmenu/migrations/0001_initial.py
cmsplugin_embeddedmenu/migrations/0002_auto__add_field_menupluginsettings_template.py
cmsplugin_embeddedmenu/migrations/0003_auto__del_field_menupluginsettings_template__add_field_menupluginsetti.py
cmsplugin_embeddedmenu/migrations/0004_auto__del_field_menupluginsettings_menu_template__add_field_menuplugin.py
cmsplugin_embeddedmenu/migrations/0005_auto__add_field_menupluginsettings_include_root.py
cmsplugin_embeddedmenu/migrations/__init__.py
cmsplugin_embeddedmenu/templates/cmsplugin_embeddedmenu/base.html
cmsplugin_embeddedmenu/templates/cmsplugin_embeddedmenu/layouts/containers/default.html
cmsplugin_embeddedmenu/templates/cmsplugin_embeddedmenu/layouts/items/default.html
cmsplugin_embeddedmenu/templates/cmsplugin_embeddedmenu/layouts/menus/default.html