Metadata-Version: 1.0
Name: cmsplugin-embedded-menu
Version: 0.0.6
Summary: DjangoCMS plugin for embedding menus in placeholders
Home-page: http://github.com/airtonix/cmsplugin-embedded-menu
Author: Zenobius Jiricek
Author-email: airtonix@gmail.com
License: BSD
Keywords: django-cms,plugin
Platform: UNKNOWN
Classifier: Development Status :: 4 - Beta
Classifier: Framework :: Django
Classifier: Intended Audience :: Developers
Classifier: License :: OSI Approved :: BSD License
Classifier: Operating System :: OS Independent
Classifier: Programming Language :: Python
Classifier: Topic :: Internet :: WWW/HTTP
